uvplot/__init__.py
uvplot/_version.py
uvplot/constants.py
uvplot/example.py
uvplot/io.py
uvplot/tests.py
uvplot/uvtable.py
uvplot-0.2.11.dist-info/LICENSE.txt
uvplot-0.2.11.dist-info/METADATA
uvplot-0.2.11.dist-info/WHEEL
uvplot-0.2.11.dist-info/top_level.txt
uvplot-0.2.11.dist-info/RECORD
