Metadata-Version: 2.1
Name: uvplot
Version: 0.2.11
Summary: Utilities for handling and plotting interferometric visibilities.
Home-page: https://github.com/mtazzari/uvplot
Author: Marco Tazzari
Author-email: mtazzari@gmail.com
License: LGPLv3
Project-URL: Bug Tracker, https://github.com/mtazzari/uvplot/issues
Keywords: science,astronomy,interferometry
Platform: UNKNOWN
Classifier: Development Status :: 5 - Production/Stable
Classifier: License :: OSI Approved :: GNU Lesser General Public License v3 (LGPLv3)
Classifier: Intended Audience :: Developers
Classifier: Intended Audience :: Science/Research
Classifier: Operating System :: MacOS :: MacOS X
Classifier: Operating System :: POSIX :: Linux
Classifier: Programming Language :: Python :: 2.7
Classifier: Programming Language :: Python :: 3.6
Classifier: Programming Language :: Python :: 3.7
Classifier: Programming Language :: Python :: 3.8
Classifier: Programming Language :: Python :: 3.9
Requires-Python: >=2.7,>=3.6
Requires-Dist: numpy (>=1.9)
Requires-Dist: matplotlib
